ak_loading/__init__.py
ak_loading/calc.py
ak_loading/html.py
ak_loading/latexize.py
ak_loading/rebar.py
ak_loading/snow_data.pkl
ak_loading/snow_loads.py
ak_loading/streamlit_page.py
ak_loading-0.0.1.dist-info/LICENSE
ak_loading-0.0.1.dist-info/WHEEL
ak_loading-0.0.1.dist-info/METADATA
ak_loading-0.0.1.dist-info/RECORD
