Metadata-Version: 2.1
Name: ak_loading
Version: 0.0.1
Summary: Load Calculators
Author-email: Arun Kishore <pypi@rpakishore.co.in>
Requires-Python: >=3.9
Classifier: License :: OSI Approved :: GNU General Public License v3 or later (GPLv3+)
Requires-Dist: forallpeople
Requires-Dist: handcalcs
Requires-Dist: streamlit
Requires-Dist: cisc_sections
Requires-Dist: pytest ; extra == "test"
Project-URL: Home, https://github.com/rpakishore/Structural-Loading
Provides-Extra: test
